whombat/__init__.py
whombat/__main__.py
whombat/app.py
whombat/cache.py
whombat/exceptions.py
whombat/plugins.py
whombat/api/__init__.py
whombat/api/annotation_projects.py
whombat/api/annotation_tasks.py
whombat/api/audio.py
whombat/api/clip_annotations.py
whombat/api/clip_evaluations.py
whombat/api/clip_predictions.py
whombat/api/clips.py
whombat/api/datasets.py
whombat/api/evaluation_sets.py
whombat/api/evaluations.py
whombat/api/features.py
whombat/api/model_runs.py
whombat/api/notes.py
whombat/api/recordings.py
whombat/api/sessions.py
whombat/api/sound_event_annotations.py
whombat/api/sound_event_evaluations.py
whombat/api/sound_event_predictions.py
whombat/api/sound_events.py
whombat/api/spectrograms.py
whombat/api/tags.py
whombat/api/user_runs.py
whombat/api/users.py
whombat/api/common/__init__.py
whombat/api/common/base.py
whombat/api/common/utils.py
whombat/api/io/__init__.py
whombat/api/io/aoef/__init__.py
whombat/api/io/aoef/annotation_projects.py
whombat/api/io/aoef/annotation_tasks.py
whombat/api/io/aoef/clip_annotations.py
whombat/api/io/aoef/clip_evaluations.py
whombat/api/io/aoef/clip_predictions.py
whombat/api/io/aoef/clips.py
whombat/api/io/aoef/common.py
whombat/api/io/aoef/datasets.py
whombat/api/io/aoef/evaluation_sets.py
whombat/api/io/aoef/evaluations.py
whombat/api/io/aoef/features.py
whombat/api/io/aoef/model_runs.py
whombat/api/io/aoef/notes.py
whombat/api/io/aoef/recordings.py
whombat/api/io/aoef/sound_event_annotations.py
whombat/api/io/aoef/sound_event_evaluations.py
whombat/api/io/aoef/sound_event_predictions.py
whombat/api/io/aoef/sound_events.py
whombat/api/io/aoef/tags.py
whombat/api/io/aoef/users.py
whombat/api/scatterplots/__init__.py
whombat/api/scatterplots/sound_event_annotations.py
whombat/core/__init__.py
whombat/core/common.py
whombat/core/files.py
whombat/core/images.py
whombat/core/spectrograms.py
whombat/filters/__init__.py
whombat/filters/annotation_projects.py
whombat/filters/annotation_tasks.py
whombat/filters/base.py
whombat-0.8.6.dist-info/METADATA
whombat-0.8.6.dist-info/WHEEL
whombat-0.8.6.dist-info/entry_points.txt
whombat-0.8.6.dist-info/licenses/AUTHORS.md
whombat-0.8.6.dist-info/licenses/LICENSE
whombat-0.8.6.dist-info/RECORD
