Metadata-Version: 2.4
Name: Whombat
Version: 0.8.6
Summary: Audio Annotation Tool
Project-URL: Homepage, https://github.com/mbsantiago/whombat
Project-URL: Documentation, https://mbsantiago.github.io/whombat/
Project-URL: Isue Tracker, https://github.com/mbsantiago/whombat/issues
Project-URL: Releases, https://github.com/mbsantiago/whombat/releases
Author-email: Santiago Martinez <santiago.mbal@gmail.com>
License:                     GNU GENERAL PUBLIC LICENSE
License-File: AUTHORS.md
License-File: LICENSE
Keywords: annotation,audio,bioacoustics,machine learning,tool
Requires-Python: >=3.11
Requires-Dist: aiosqlite>=0.20.0
Requires-Dist: alembic>=1.13.2
Requires-Dist: asyncache>=0.3.1
Requires-Dist: bcrypt==4.0.1
Requires-Dist: cachetools>=5.5.0
Requires-Dist: colorama>=0.4.6
Requires-Dist: fastapi-pagination>=0.12.26
Requires-Dist: fastapi-users[sqlalchemy]>=12.1.3
Requires-Dist: fastapi[standard]>=0.112.2
Requires-Dist: passlib>=1.7.4
Requires-Dist: pydantic-settings>=2.4.0
Requires-Dist: setuptools>=75.1.0
Requires-Dist: soundevent[all]>=2.1.1
Requires-Dist: uvicorn[standard]>=0.30.6
Provides-Extra: postgre
Requires-Dist: asyncpg>=0.29.0; extra == 'postgre'
Requires-Dist: psycopg2-binary>=2.9.9; extra == 'postgre'
